pretix_extended_api/__init__.py
pretix_extended_api/apps.py
pretix_extended_api/locale/de/LC_MESSAGES/django.po
pretix_extended_api/locale/de_Informal/.gitkeep
pretix_extended_api/locale/de_Informal/LC_MESSAGES/django.po
pretix_extended_api/signals.py
pretix_extended_api/static/pretix_extended_api/.gitkeep
pretix_extended_api/templates/pretix_extended_api/.gitkeep
pretix_extended_api/urls.py
pretix_extended_api/views/__init__.py
pretix_extended_api/views/orders.py
pretix_extended_api/views/permissions.py
pretix_extended_api/views/serializers.py
pretix_extended_api/views/tickets.py
pretix_extended_api/views/vouchers.py
pretix_plugin_extended_api-0.1.14.dist-info/METADATA
pretix_plugin_extended_api-0.1.14.dist-info/WHEEL
pretix_plugin_extended_api-0.1.14.dist-info/entry_points.txt
pretix_plugin_extended_api-0.1.14.dist-info/licenses/LICENSE
pretix_plugin_extended_api-0.1.14.dist-info/RECORD
