Metadata-Version: 2.1
Name: pretix-plugin-extended-api
Version: 0.1.14
Summary: Extend the REST API to expose more information needed by the PyCon Italia repository.
Author: Python Italia
License: MIT
Requires-Python: <4.0,>=3.9
